collinear/__init__.py
collinear/_version.py
collinear/client.py
collinear/assess/__init__.py
collinear/assess/local.py
collinear/clients/__init__.py
collinear/clients/assistant_client.py
collinear/clients/steering_client.py
collinear/common/__init__.py
collinear/common/exceptions.py
collinear/redteam/__init__.py
collinear/redteam/client.py
collinear/redteam/orchestrator.py
collinear/redteam/payloads.py
collinear/redteam/policies.py
collinear/redteam/schemas.py
collinear/schemas/__init__.py
collinear/schemas/assessment.py
collinear/schemas/traitmix.py
collinear/simulate/__init__.py
collinear/simulate/conversation.py
collinear/simulate/payloads.py
collinear/simulate/progress.py
collinear/simulate/runner.py
collinear-1.0.25.dist-info/METADATA
collinear-1.0.25.dist-info/WHEEL
collinear-1.0.25.dist-info/licenses/LICENSE
collinear-1.0.25.dist-info/RECORD
