Metadata-Version: 2.4
Name: collinear
Version: 1.0.25
Summary: Collinear public Python library
Project-URL: Homepage, https://www.collinear.ai/
Author-email: Quinten <quinten@collinear.ai>
License: Apache License
License-File: LICENSE
Classifier: License :: OSI Approved :: Apache Software License
Classifier: Operating System :: OS Independent
Classifier: Programming Language :: Python :: 3
Requires-Python: >=3.10
Requires-Dist: httpx==0.27.2
Requires-Dist: openai==1.106.1
Requires-Dist: pydantic==2.11.7
Requires-Dist: python-dotenv>=1.1.1
Requires-Dist: requests==2.32.5
